docs/images/diagrams/laktory_diagram.png
docs/images/logos/laktory_logo_sg.png
docs/images/logos/laktory_logo_sg_ltb.png
docs/images/logos/laktory_logo_sw.png
docs/images/logos/laktory_logo_sw_ltw.png
laktory/__init__.py
laktory/_cache.py
laktory/_logger.py
laktory/_parsers.py
laktory/_settings.py
laktory/_useragent.py
laktory/_version.py
laktory/constants.py
laktory/datetime.py
laktory/enums.py
laktory/exceptions.py
laktory/sqlparser.py
laktory/typing.py
laktory/version.py
laktory/_testing/__init__.py
laktory/_testing/get_dfs.py
laktory/_testing/paths.py
laktory/api/__init__.py
laktory/cli/__init__.py
laktory/cli/_build.py
laktory/cli/_common.py
laktory/cli/_deploy.py
laktory/cli/_destroy.py
laktory/cli/_init.py
laktory/cli/_preview.py
laktory/cli/_quickstart.py
laktory/cli/_run.py
laktory/cli/_validate.py
laktory/cli/_version.py
laktory/cli/app.py
laktory/dispatcher/__init__.py
laktory/dispatcher/databricksjobrunner.py
laktory/dispatcher/databrickspipelinerunner.py
laktory/dispatcher/dispatcher.py
laktory/dispatcher/dispatcherrunner.py
laktory/models/__init__.py
laktory/models/basechild.py
laktory/models/basemodel.py
laktory/models/dtypes.py
laktory/models/pipelinechild.py
laktory/models/readerwritermethod.py
laktory/models/azurenative/storageblob.py
laktory/models/dataframe/__init__.py
laktory/models/dataframe/dataframecolumn.py
laktory/models/dataframe/dataframecolumnexpr.py
laktory/models/dataframe/dataframeexpr.py
laktory/models/dataframe/dataframemethod.py
laktory/models/dataframe/dataframeschema.py
laktory/models/dataframe/dataframetransformer.py
laktory/models/dataquality/__init__.py
laktory/models/dataquality/check.py
laktory/models/dataquality/expectation.py
laktory/models/datasinks/__init__.py
laktory/models/datasinks/basedatasink.py
laktory/models/datasinks/filedatasink.py
laktory/models/datasinks/hivemetastoredatasink.py
laktory/models/datasinks/mergecdcoptions.py
laktory/models/datasinks/pipelineviewdatasink.py
laktory-0.8.17.dist-info/METADATA
laktory-0.8.17.dist-info/WHEEL
laktory-0.8.17.dist-info/entry_points.txt
laktory-0.8.17.dist-info/licenses/LICENSE.md
laktory-0.8.17.dist-info/RECORD
