Metadata-Version: 2.4
Name: laktory
Version: 0.8.17
Summary: An ETL and DataOps framework for building a lakehouse
Project-URL: Homepage, https://github.com/okube-ai/laktory
Project-URL: Documentation, https://www.laktory.ai
Project-URL: Repository, https://github.com/okube-ai/laktory
Project-URL: Bug Tracker, https://github.com/opencubes-ai/laktory/issues
Author-email: Olivier Soucy <olivier.soucy@okube.ai>
License: MIT License
License-File: LICENSE.md
Keywords: apache-spark,data-pipeline,dataframes,etl,infrastructure-as-code,polars,python,sql
Classifier: Development Status :: 4 - Beta
Classifier: Framework :: Pydantic :: 2
Classifier: License :: OSI Approved :: MIT License
Classifier: Operating System :: OS Independent
Classifier: Programming Language :: Python :: 3
Classifier: Programming Language :: Python :: 3.10
Classifier: Programming Language :: Python :: 3.11
Classifier: Programming Language :: Python :: 3.12
Classifier: Programming Language :: Python :: 3.13
Requires-Python: >=3.10
Requires-Dist: inflect
Requires-Dist: narwhals>=1.46
Requires-Dist: networkx
Requires-Dist: planck>=0.0.8
Requires-Dist: platformdirs
Requires-Dist: prompt-toolkit
Requires-Dist: pydantic-settings
Requires-Dist: pydantic>=2
Requires-Dist: pyyaml
Requires-Dist: sqlglot[rs]
Requires-Dist: typer
Requires-Dist: tzdata; sys_platform == 'win32'
Provides-Extra: databricks
Requires-Dist: databricks-sdk; extra == 'databricks'
Provides-Extra: dev
Requires-Dist: flit; extra == 'dev'
Requires-Dist: griffe-fieldz; extra == 'dev'
Requires-Dist: mkdocs; extra == 'dev'
Requires-Dist: mkdocs-material; extra == 'dev'
Requires-Dist: mkdocs-video; extra == 'dev'
Requires-Dist: mkdocstrings[python]; extra == 'dev'
Requires-Dist: pandas; extra == 'dev'
Requires-Dist: plotly; extra == 'dev'
Requires-Dist: pre-commit; extra == 'dev'
Requires-Dist: pytest; extra == 'dev'
Requires-Dist: pytest-cov; extra == 'dev'
Requires-Dist: pytest-examples; extra == 'dev'
Requires-Dist: pytest-mock; extra == 'dev'
Requires-Dist: ruff; extra == 'dev'
Requires-Dist: yfinance; extra == 'dev'
Provides-Extra: polars
Requires-Dist: deltalake; extra == 'polars'
Requires-Dist: polars<1.32.1; extra == 'polars'
Requires-Dist: sqlparse; extra == 'polars'
Provides-Extra: pulumi
Requires-Dist: pulumi; extra == 'pulumi'
Requires-Dist: pulumi-databricks>=1.49; extra == 'pulumi'
Provides-Extra: pyspark
Requires-Dist: delta-spark; extra == 'pyspark'
Requires-Dist: pyarrow; extra == 'pyspark'
Requires-Dist: pyspark[connect]<4.0; extra == 'pyspark'
Requires-Dist: setuptools; (python_version >= '3.12') and extra == 'pyspark'
